kk/__init__.py
kk/handler.py
kk/index.py
kk/static/favicon.ico
kk/static/img/apk.png
kk/static/img/audio.png
kk/static/img/c.png
kk/static/img/cpp.png
kk/static/img/css.png
kk/static/img/database.png
kk/static/img/dmg.png
kk/static/img/docx.png
kk/static/img/exe.png
kk/static/img/file.png
kk/static/img/folder.png
kk/static/img/golang.png
kk/static/img/html.png
kk/static/img/image.png
kk/static/img/ini.png
kk/static/img/iso.png
kk/static/img/java.png
kk/static/img/javascript.png
kk/static/img/json.png
kk/static/img/kindle.png
kk/static/img/markdown.png
kk/static/img/pdf.png
kk/static/img/pptx.png
kk/static/img/python.png
kk/static/img/rar.png
kk/static/img/shell.png
kk/static/img/txt.png
kk/static/img/video.png
kk/static/img/vue.png
kk/static/img/xlsx.png
kk/static/img/xml.png
kk/static/img/yaml.png
kk/static/img/zip.png
kk/static/img2/apk.png
kk/static/img2/audio.png
kk/static/img2/c.png
kk/static/img2/cpp.png
kk/static/img2/css.png
kk/static/img2/database.png
kk/static/img2/dmg.png
kk/static/img2/docx.png
kk/static/img2/exe.png
kk/static/img2/file.png
kk/static/img2/folder.png
kk/static/img2/golang.png
kk/static/img2/html.png
kk/static/img2/image.png
kk/static/img2/ini.png
kk/static/img2/iso.png
kk/static/img2/java.png
kk/static/img2/javascript.png
kk/static/img2/json.png
kk/static/img2/kindle.png
kk/static/img2/markdown.png
kk/static/img2/pdf.png
kk/static/img2/php.png
kk/static/img2/pptx.png
kk/static/img2/python.png
kk/static/img2/shell.png
kk/static/img2/txt.png
kk/static/img2/video.png
kk/static/img2/vue.png
kk/static/img2/xlsx.png
kk/static/img2/xml.png
kk/static/img2/yaml.png
kk/static/img2/zip.png
kk/static/src/css/APlayer.min.css
kk/static/src/css/DPlayer.min.css
kk/static/src/css/iconfont.css
kk/static/src/css/iconfont.eot
kk/static/src/css/iconfont.svg
kk/static/src/css/iconfont.ttf
kk/static/src/css/iconfont.woff
kk/static/src/css/iconfont.woff2
kk/static/src/css/markdown.css
kk/static/src/css/monokai_sublime.css
kk/static/src/css/style.css
kk-1.0.8.dist-info/METADATA
kk-1.0.8.dist-info/WHEEL
kk-1.0.8.dist-info/entry_points.txt
kk-1.0.8.dist-info/top_level.txt
kk-1.0.8.dist-info/RECORD
