Metadata-Version: 2.2
Name: kk
Version: 1.0.8
Summary: a simple file server
Home-page: https://github.com/zkdfbb/kk
Author: digua
Author-email: zkdfbb@qq.com
License: GPL
Classifier: Development Status :: 4 - Beta
Classifier: Intended Audience :: Developers
Classifier: Topic :: Software Development :: Build Tools
Classifier: License :: OSI Approved :: MIT License
Classifier: Programming Language :: Python :: 3.6
Classifier: Programming Language :: Python :: 3.7
Classifier: Programming Language :: Python :: 3.8
Classifier: Programming Language :: Python :: 3.9
Requires-Python: >=3.6
Requires-Dist: markdown
Requires-Dist: psutil
Requires-Dist: kkutils>=1.6.8
Dynamic: author
Dynamic: author-email
Dynamic: classifier
Dynamic: home-page
Dynamic: license
Dynamic: requires-dist
Dynamic: requires-python
Dynamic: summary
